zid/__init__.py
zid/_lib.cpython-314-aarch64-linux-gnu.so
zid/_lib.pyi
zid/py.typed
zid-1.5.0.dist-info/METADATA
zid-1.5.0.dist-info/WHEEL
zid-1.5.0.dist-info/RECORD
